pkgviz/__init__.py
pkgviz/cli.py
pkgviz/engine.py
pkgviz/types.py
pkgviz/utils.py
pkgviz_python-0.1.5.dist-info/LICENSE
pkgviz_python-0.1.5.dist-info/METADATA
pkgviz_python-0.1.5.dist-info/WHEEL
pkgviz_python-0.1.5.dist-info/entry_points.txt
pkgviz_python-0.1.5.dist-info/top_level.txt
pkgviz_python-0.1.5.dist-info/RECORD
