Metadata-Version: 2.1
Name: pkgviz-python
Version: 0.1.5
Summary: Framework to visualise python packages
Home-page: https://github.com/AjinkyaIndulkar/pkgviz-python
Author: Ajinkya Indulkar
Author-email: 26824103+AjinkyaIndulkar@users.noreply.github.com
License: MIT License
Classifier: Programming Language :: Python :: 3
Classifier: License :: OSI Approved :: MIT License
Classifier: Operating System :: OS Independent
Requires-Python: <3.11,>=3.7
License-File: LICENSE
Requires-Dist: click
Requires-Dist: graphviz
Requires-Dist: rich
